DMI.py
ambra_ts_tools/__init__.py
ambra_ts_tools/authenticate_ambra.py
ambra_ts_tools/copyViewerSettings.py
ambra_ts_tools/log_parser.py
ambra_ts_tools/reconcilliation.py
ambra_ts_tools/runner.py
ambra_ts_tools/setup.py
ambra_ts_tools/study_bulk_share_multithreaded.py
ambra_ts_tools/study_uid_image_count_check.py
ambra_ts_tools/thin_add.py
ambra_ts_tools/update_ui_json_setting copy.py
ambra_ts_tools/update_ui_json_setting.py
ambra_ts_tools/upload_wrapped_csv.py
ambra_ts_tools/Ambra_Clone/Clone.py
ambra_ts_tools/Ambra_Clone/__init__.py
ambra_ts_tools/Ambra_Clone/V2/__init__.py
ambra_ts_tools/Ambra_Clone/V2/account_configuration.py
ambra_ts_tools/Ambra_Clone/V2/ambra_environment.py
ambra_ts_tools/Ambra_Clone/V2/clone.py
ambra_ts_tools-0.1.10.dist-info/LICENSE
ambra_ts_tools-0.1.10.dist-info/METADATA
ambra_ts_tools-0.1.10.dist-info/WHEEL
ambra_ts_tools-0.1.10.dist-info/top_level.txt
ambra_ts_tools-0.1.10.dist-info/RECORD
