Metadata-Version: 2.1
Name: ambra-ts-tools
Version: 0.1.10
Summary: Ambra Clone tools for technical services
Author-email: Ethan York <ethan.york@intelerad.com>
Project-URL: Homepage, https://github.com/dicomgrid/tech-services-scripts
Classifier: Programming Language :: Python :: 3
Classifier: License :: OSI Approved :: Apache Software License
Classifier: Operating System :: OS Independent
Requires-Python: >=3.7
License-File: LICENSE
